mfaliquot/__init__.py
mfaliquot/aliquot.py
mfaliquot/myutils.py
mfaliquot/numtheory.py
mfaliquot/sequence.py
mfaliquot-0.0.1.post2.dist-info/METADATA
mfaliquot-0.0.1.post2.dist-info/WHEEL
mfaliquot-0.0.1.post2.dist-info/DESCRIPTION.rst
mfaliquot-0.0.1.post2.dist-info/top_level.txt
mfaliquot-0.0.1.post2.dist-info/RECORD
mfaliquot-0.0.1.post2.dist-info/metadata.json
