Metadata-Version: 2.0
Name: mfaliquot
Version: 0.0.1.post2
Summary: A software 'suite' relating to aliquot sequences and their analysis
Home-page: https://github.com/dubslow/MersenneForumAliquot
Author: Bill Winslow
Author-email: Dubslow @ mersenneforum.org
License: GPLv3+
Keywords: aliquot sequences mersenne mersenneforum perfect numbers
Platform: UNKNOWN
Classifier: Development Status :: 3 - Alpha
Classifier: Intended Audience :: Science/Research
Classifier: Intended Audience :: Developers
Classifier: Topic :: Scientific/Engineering :: Mathematics
Classifier: License :: OSI Approved :: GNU General Public License v3 or later (GPLv3+)
Classifier: Programming Language :: Python :: 3
Classifier: Programming Language :: Python :: 3.3
Classifier: Programming Language :: Python :: 3.4
Classifier: Programming Language :: Python :: 3 :: Only
